acert_nlsl.libs/libgfortran-83c28eba.so.5.0.0
acert_nlsl.libs/libquadmath-2284e583.so.0.0.0
nlsl/__init__.py
nlsl/cli.py
nlsl/data.py
nlsl/fortrancore.cpython-313-x86_64-linux-gnu.so
nlsl/tests/tests/5pc.par
nlsl/tests/tests/__init__.py
nlsl/tests/tests/c16pc371e.run
nlsl/tests/tests/csl.par
nlsl/tests/tests/sampl1.dat
nlsl/tests/tests/sampl1.run
nlsl/tests/tests/sampl2.run
nlsl/tests/tests/sampl200.dat
nlsl/tests/tests/sampl290.dat
nlsl/tests/tests/sampl2a.run
nlsl/tests/tests/sampl3.dat
nlsl/tests/tests/sampl3.run
nlsl/tests/tests/sampl3a.run
nlsl/tests/tests/sampl4.dat
nlsl/tests/tests/sampl4.run
nlsl/tests/tests/sampl4_reference.py
nlsl/tests/tests/sampl5.run
nlsl/tests/tests/sampl500.dat
nlsl/tests/tests/sampl590.dat
nlsl/tests/tests/test_current_spectrum.py
nlsl/tests/tests/test_data_helpers.py
nlsl/tests/tests/test_procline_aliases.py
nlsl/tests/tests/test_procline_multisite.py
nlsl/tests/tests/test_procline_set.py
nlsl/tests/tests/test_runexamples.py
nlsl/tests/tests/test_sampl4_best_parameters.py
nlsl/tests/tests/test_sampl4_fit.py
nlsl/tests/tests/test_sample1.py
acert_nlsl-0.1.0.11.dist-info/LICENSE.md
acert_nlsl-0.1.0.11.dist-info/METADATA
acert_nlsl-0.1.0.11.dist-info/WHEEL
acert_nlsl-0.1.0.11.dist-info/entry_points.txt
acert_nlsl-0.1.0.11.dist-info/RECORD
