Metadata-Version: 2.1
Name: acert-nlsl
Version: 0.1.0.11
Summary: the ACERT NLSL package, now wrapped up in python!
Author: NLSL development team
License: Copyright (c) 2015, ACERT
Requires-Dist: sympy
Requires-Dist: numpy>=1.26.5
Requires-Dist: scipy
Requires-Dist: matplotlib
Requires-Dist: tables
